README.md
setup.cfg
setup.py
benchmarks/__init__.py
benchmarks/benchmark.py
e4client/__init__.py
e4client/client.py
e4client/example.py
e4client/exceptions.py
e4client/protocol.py
open_e4_client.egg-info/PKG-INFO
open_e4_client.egg-info/SOURCES.txt
open_e4_client.egg-info/dependency_links.txt
open_e4_client.egg-info/top_level.txt