Metadata-Version: 2.1
Name: open-e4-client
Version: 0.1.1
Summary: Simple, pure Python 3.7 client for the Empatica E4 streaming server.
Home-page: https://github.com/molguin92/open-e4-client
Author: Manuel Olguin Munoz
Author-email: molguin@kth.se
License: UNKNOWN
Download-URL: https://github.com/molguin92/open-e4-client/archive/0.1.1.tar.gz
Platform: UNKNOWN
Classifier: Programming Language :: Python :: 3
Classifier: Development Status :: 2 - Pre-Alpha
Classifier: License :: OSI Approved :: Apache Software License
Classifier: Operating System :: POSIX :: Linux
Requires-Python: >=3.7
